Workbook

Sheet Transactions
A1: PETTY CASH BOOK
A2: Month / Year: | E2: 46113 | I2: Project: | K2: Discovery Dunes
A3: TOTAL CASH-IN (AED) | E3: TOTAL ADVANCED (AED) | I3: TOTAL RETURNED (AED) | M3: CLOSING BALANCE (AED)
A4: =E5+SUM(C8:C3006) -> 13656.81 | E4: =SUM(H8:H3006) -> 9187 | I4: =SUM(N8:N3006) -> 3900 | M4: =E5+SUM(C8:C3006)-SUM(H8:H3006)+SUM(N8:N3006)-SUM(R8:R3006) -> 8269.81
A5: Opening Balance (Cash in Hand): | E5: 5524 | I5: ← Update this when opening balance changes
A6: CASH-IN | D6: VOUCHER / ADVANCE / EXPENSE / SETTLEMENT
A7: Date | B7: Description / Ref | C7: Cash-In Amt | D7: Ref. No. | E7: Voucher Date | F7: Payee / Worker | G7: Purpose | H7: Adv. Amount | I7: Fuel | J7: Service / Labour | K7: Materials | L7: Food Allowance | M7: Others | N7: Balance Returned | O7: Actual Expense | P7: Variance (Adv−Exp) | Q7: Reimb. Amount | R7: Reimb. Paid | S7: Change Due Back
A8: 46114 | B8: Balance c/d | C8: 2132.81 | D8: V-001 | E8: 46041 | F8: Rey | G8: Advance | H8: 410 | N8: 0 | O8: =IF(G8="Reimbursement ","",I8+J8+K8+L8+M8) -> 0 | P8: =IF(G8="Reimbursement ","",H8-O8) -> 410 | S8: =IF(OR(R8="",Q8=""),0,IF(R8>Q8,R8-Q8,0)) -> 0
A9: 46114 | B9: Received from HO | C9: 5000 | D9: V-002 | E9: 46042 | F9: Ben | G9: Advance | H9: 18 | N9: 0 | O9: =IF(G9="Reimbursement ","",I9+J9+K9+L9+M9) -> 0 | P9: =IF(G9="Reimbursement ","",H9-O9) -> 18 | S9: =IF(OR(R9="",Q9=""),0,IF(R9>Q9,R9-Q9,0)) -> 0
C10: 1000 | D10: V-003 | E10: 46109 | F10: Cal | G10: Balance | H10: 2 | N10: 0 | O10: =IF(G10="Reimbursement ","",I10+J10+K10+L10+M10) -> 0 | P10: =IF(G10="Reimbursement ","",H10-O10) -> 2 | S10: =IF(OR(R10="",Q10=""),0,IF(R10>Q10,R10-Q10,0)) -> 0
D11: V-004 | E11: 46107 | F11: Dan | G11: Balance | H11: 10 | N11: 0 | O11: =IF(G11="Reimbursement ","",I11+J11+K11+L11+M11) -> 0 | P11: =IF(G11="Reimbursement ","",H11-O11) -> 10 | S11: =IF(OR(R11="",Q11=""),0,IF(R11>Q11,R11-Q11,0)) -> 0
D12: V-005 | E12: 46082 | F12: Eli | G12: Advance | H12: 500 | N12: 0 | O12: =IF(G12="Reimbursement ","",I12+J12+K12+L12+M12) -> 0 | P12: =IF(G12="Reimbursement ","",H12-O12) -> 500 | S12: =IF(OR(R12="",Q12=""),0,IF(R12>Q12,R12-Q12,0)) -> 0
D13: V-006 | E13: 46083 | F13: Ian | G13: Advance | H13: 500 | N13: 0 | O13: =IF(G13="Reimbursement ","",I13+J13+K13+L13+M13) -> 0 | P13: =IF(G13="Reimbursement ","",H13-O13) -> 500 | S13: =IF(OR(R13="",Q13=""),0,IF(R13>Q13,R13-Q13,0)) -> 0
D14: V-007 | E14: 46084 | F14: Jay | G14: Advance | H14: 1000 | N14: 0 | O14: =IF(G14="Reimbursement ","",I14+J14+K14+L14+M14) -> 0 | P14: =IF(G14="Reimbursement ","",H14-O14) -> 1000 | S14: =IF(OR(R14="",Q14=""),0,IF(R14>Q14,R14-Q14,0)) -> 0
D15: V-008 | E15: 46085 | F15: Kai | G15: Returned | N15: 200 | O15: =IF(G15="Reimbursement ","",I15+J15+K15+L15+M15) -> 0 | P15: =IF(G15="Reimbursement ","",H15-O15) -> 0 | S15: =IF(OR(R15="",Q15=""),0,IF(R15>Q15,R15-Q15,0)) -> 0
D16: V-009 | E16: 46086 | F16: Leo | G16: Advance | H16: 1000 | N16: 500 | O16: =IF(G16="Reimbursement ","",I16+J16+K16+L16+M16) -> 0 | P16: =IF(G16="Reimbursement ","",H16-O16) -> 1000 | S16: =IF(OR(R16="",Q16=""),0,IF(R16>Q16,R16-Q16,0)) -> 0
D17: V-010 | E17: 46087 | F17: Max | G17: Returned | N17: 300 | O17: =IF(G17="Reimbursement ","",I17+J17+K17+L17+M17) -> 0 | P17: =IF(G17="Reimbursement ","",H17-O17) -> 0 | S17: =IF(OR(R17="",Q17=""),0,IF(R17>Q17,R17-Q17,0)) -> 0
D18: V-011 | E18: 46088 | F18: Neo | G18: Reimbursement | N18: 0 | O18: =IF(G18="Reimbursement ","",I18+J18+K18+L18+M18) | P18: =IF(G18="Reimbursement ","",H18-O18) | Q18: 600 | S18: =IF(OR(R18="",Q18=""),0,IF(R18>Q18,R18-Q18,0)) -> 0
D19: V-012 | E19: 46089 | F19: Oli | G19: Advance | H19: 1000 | N19: 0 | O19: =IF(G19="Reimbursement ","",I19+J19+K19+L19+M19) -> 0 | P19: =IF(G19="Reimbursement ","",H19-O19) -> 1000 | S19: =IF(OR(R19="",Q19=""),0,IF(R19>Q19,R19-Q19,0)) -> 0
D20: V-013 | E20: 46090 | F20: Ray | G20: Returned | H20: 1000 | J20: 100 | N20: 400 | O20: =IF(G20="Reimbursement ","",I20+J20+K20+L20+M20) -> 100 | P20: =IF(G20="Reimbursement ","",H20-O20) -> 900 | S20: =IF(OR(R20="",Q20=""),0,IF(R20>Q20,R20-Q20,0)) -> 0
D21: V-014 | E21: 46091 | F21: Sam | G21: Advance | H21: 1500 | I21: 300 | N21: 1000 | O21: =IF(G21="Reimbursement ","",I21+J21+K21+L21+M21) -> 300 | P21: =IF(G21="Reimbursement ","",H21-O21) -> 1200 | S21: =IF(OR(R21="",Q21=""),0,IF(R21>Q21,R21-Q21,0)) -> 0
D22: V-015 | E22: 46092 | F22: Tom | G22: Reimbursement | N22: 0 | O22: =IF(G22="Reimbursement ","",I22+J22+K22+L22+M22) | P22: =IF(G22="Reimbursement ","",H22-O22) | Q22: 2000 | S22: =IF(OR(R22="",Q22=""),0,IF(R22>Q22,R22-Q22,0)) -> 0
D23: V-016 | E23: 46093 | F23: Vic | G23: Advance | H23: 500 | N23: 0 | O23: =IF(G23="Reimbursement ","",I23+J23+K23+L23+M23) -> 0 | P23: =IF(G23="Reimbursement ","",H23-O23) -> 500 | S23: =IF(OR(R23="",Q23=""),0,IF(R23>Q23,R23-Q23,0)) -> 0
D24: V-017 | E24: 46094 | F24: Zac | G24: Advance | H24: 122 | N24: 0 | O24: =IF(G24="Reimbursement ","",I24+J24+K24+L24+M24) -> 0 | P24: =IF(G24="Reimbursement ","",H24-O24) -> 122 | S24: =IF(OR(R24="",Q24=""),0,IF(R24>Q24,R24-Q24,0)) -> 0
D25: V-017 | E25: 46094 | F25: Roy | G25: Advance | H25: 123 | O25: =IF(G25="Reimbursement ","",I25+J25+K25+L25+M25) -> 0 | P25: =IF(G25="Reimbursement ","",H25-O25) -> 123 | S25: =IF(OR(R25="",Q25=""),0,IF(R25>Q25,R25-Q25,0)) -> 0
D26: V-018 | E26: 46095 | F26: Asa | G26: Advance | H26: 124 | O26: =IF(G26="Reimbursement ","",I26+J26+K26+L26+M26) -> 0 | P26: =IF(G26="Reimbursement ","",H26-O26) -> 124 | S26: =IF(OR(R26="",Q26=""),0,IF(R26>Q26,R26-Q26,0)) -> 0
D27: V-019 | E27: 46096 | F27: Gil | G27: Advance | H27: 125 | O27: =IF(G27="Reimbursement ","",I27+J27+K27+L27+M27) -> 0 | P27: =IF(G27="Reimbursement ","",H27-O27) -> 125 | S27: =IF(OR(R27="",Q27=""),0,IF(R27>Q27,R27-Q27,0)) -> 0
D28: V-020 | E28: 46097 | F28: Joe | G28: Advance | H28: 126 | N28: 0 | O28: =IF(G28="Reimbursement ","",I28+J28+K28+L28+M28) -> 0 | P28: =IF(G28="Reimbursement ","",H28-O28) -> 126 | S28: =IF(OR(R28="",Q28=""),0,IF(R28>Q28,R28-Q28,0)) -> 0
D29: V-021 | E29: 46098 | F29: Ken | G29: Advance | H29: 127 | O29: =IF(G29="Reimbursement ","",I29+J29+K29+L29+M29) -> 0 | P29: =IF(G29="Reimbursement ","",H29-O29) -> 127 | S29: =IF(OR(R29="",Q29=""),0,IF(R29>Q29,R29-Q29,0)) -> 0
D30: V-022 | E30: 46099 | F30: Lou | G30: Advance | H30: 1000 | I30: 100 | J30: 100 | K30: 100 | N30: 1000 | O30: =IF(G30="Reimbursement ","",I30+J30+K30+L30+M30) -> 300 | P30: =IF(G30="Reimbursement ","",H30-O30) -> 700 | S30: =IF(OR(R30="",Q30=""),0,IF(R30>Q30,R30-Q30,0)) -> 0
D31: V-023 | E31: 46100 | F31: Rex | G31: Reimbursement | I31: 10 | J31: 20 | K31: 30 | L31: 15 | M31: 40 | N31: 500 | O31: =IF(G31="Reimbursement ","",I31+J31+K31+L31+M31) | P31: =IF(G31="Reimbursement ","",H31-O31) | Q31: 1000 | R31: 100 | S31: =IF(OR(R31="",Q31=""),0,IF(R31>Q31,R31-Q31,0)) -> 0
O32: =IF(G32="Reimbursement ","",I32+J32+K32+L32+M32) -> 0 | P32: =IF(G32="Reimbursement ","",H32-O32) -> 0 | S32: =IF(OR(R32="",Q32=""),0,IF(R32>Q32,R32-Q32,0)) -> 0
O33: =IF(G33="Reimbursement ","",I33+J33+K33+L33+M33) -> 0 | P33: =IF(G33="Reimbursement ","",H33-O33) -> 0 | S33: =IF(OR(R33="",Q33=""),0,IF(R33>Q33,R33-Q33,0)) -> 0
O34: =IF(G34="Reimbursement ","",I34+J34+K34+L34+M34) -> 0 | P34: =IF(G34="Reimbursement ","",H34-O34) -> 0 | S34: =IF(OR(R34="",Q34=""),0,IF(R34>Q34,R34-Q34,0)) -> 0
O35: =IF(G35="Reimbursement ","",I35+J35+K35+L35+M35) -> 0 | P35: =IF(G35="Reimbursement ","",H35-O35) -> 0 | S35: =IF(OR(R35="",Q35=""),0,IF(R35>Q35,R35-Q35,0)) -> 0
O36: =IF(G36="Reimbursement ","",I36+J36+K36+L36+M36) -> 0 | P36: =IF(G36="Reimbursement ","",H36-O36) -> 0 | S36: =IF(OR(R36="",Q36=""),0,IF(R36>Q36,R36-Q36,0)) -> 0
O37: =IF(G37="Reimbursement ","",I37+J37+K37+L37+M37) -> 0 | P37: =IF(G37="Reimbursement ","",H37-O37) -> 0 | S37: =IF(OR(R37="",Q37=""),0,IF(R37>Q37,R37-Q37,0)) -> 0
O38: =IF(G38="Reimbursement ","",I38+J38+K38+L38+M38) -> 0 | P38: =IF(G38="Reimbursement ","",H38-O38) -> 0 | S38: =IF(OR(R38="",Q38=""),0,IF(R38>Q38,R38-Q38,0)) -> 0
O39: =IF(G39="Reimbursement ","",I39+J39+K39+L39+M39) -> 0 | P39: =IF(G39="Reimbursement ","",H39-O39) -> 0 | S39: =IF(OR(R39="",Q39=""),0,IF(R39>Q39,R39-Q39,0)) -> 0
O40: =IF(G40="Reimbursement ","",I40+J40+K40+L40+M40) -> 0 | P40: =IF(G40="Reimbursement ","",H40-O40) -> 0 | S40: =IF(OR(R40="",Q40=""),0,IF(R40>Q40,R40-Q40,0)) -> 0
O41: =IF(G41="Reimbursement ","",I41+J41+K41+L41+M41) -> 0 | P41: =IF(G41="Reimbursement ","",H41-O41) -> 0 | S41: =IF(OR(R41="",Q41=""),0,IF(R41>Q41,R41-Q41,0)) -> 0
O42: =IF(G42="Reimbursement ","",I42+J42+K42+L42+M42) -> 0 | P42: =IF(G42="Reimbursement ","",H42-O42) -> 0 | S42: =IF(OR(R42="",Q42=""),0,IF(R42>Q42,R42-Q42,0)) -> 0
O43: =IF(G43="Reimbursement ","",I43+J43+K43+L43+M43) -> 0 | P43: =IF(G43="Reimbursement ","",H43-O43) -> 0 | S43: =IF(OR(R43="",Q43=""),0,IF(R43>Q43,R43-Q43,0)) -> 0
... O133: =IF(G133="Reimbursement ","",I133+J133+K133+L133+M133) -> 0 | P133: =IF(G133="Reimbursement ","",H133-O133) -> 0 | S133: =IF(OR(R133="",Q133=""),0,IF(R133>Q133,R133-Q133,0)) -> 0
O134: =#N/A -> #N/A | P134: =#N/A -> #N/A | S134: =IF(OR(R134="",Q134=""),0,IF(R134>Q134,R134-Q134,0)) -> 0
O135: =IF(G135="Reimbursement ","",I135+J135+K135+L135+M135) -> 0 | P135: =IF(G135="Reimbursement ","",H135-O135) -> 0 | S135: =IF(OR(R135="",Q135=""),0,IF(R135>Q135,R135-Q135,0)) -> 0
O136: =IF(G136="Reimbursement ","",I136+J136+K136+L136+M136) -> 0 | P136: =IF(G136="Reimbursement ","",H136-O136) -> 0 | S136: =IF(OR(R136="",Q136=""),0,IF(R136>Q136,R136-Q136,0)) -> 0
O137: =IF(G137="Reimbursement ","",I137+J137+K137+L137+M137) -> 0 | P137: =IF(G137="Reimbursement ","",H137-O137) -> 0 | S137: =IF(OR(R137="",Q137=""),0,IF(R137>Q137,R137-Q137,0)) -> 0
O138: =IF(G138="Reimbursement ","",I138+J138+K138+L138+M138) -> 0 | P138: =IF(G138="Reimbursement ","",H138-O138) -> 0 | S138: =IF(OR(R138="",Q138=""),0,IF(R138>Q138,R138-Q138,0)) -> 0
O139: =IF(G139="Reimbursement ","",I139+J139+K139+L139+M139) -> 0 | P139: =IF(G139="Reimbursement ","",H139-O139) -> 0 | S139: =IF(OR(R139="",Q139=""),0,IF(R139>Q139,R139-Q139,0)) -> 0
O140: =IF(G140="Reimbursement ","",I140+J140+K140+L140+M140) -> 0 | P140: =IF(G140="Reimbursement ","",H140-O140) -> 0 | S140: =IF(OR(R140="",Q140=""),0,IF(R140>Q140,R140-Q140,0)) -> 0
O141: =IF(G141="Reimbursement ","",I141+J141+K141+L141+M141) -> 0 | P141: =IF(G141="Reimbursement ","",H141-O141) -> 0 | S141: =IF(OR(R141="",Q141=""),0,IF(R141>Q141,R141-Q141,0)) -> 0
O142: =IF(G142="Reimbursement ","",I142+J142+K142+L142+M142) -> 0 | P142: =IF(G142="Reimbursement ","",H142-O142) -> 0 | S142: =IF(OR(R142="",Q142=""),0,IF(R142>Q142,R142-Q142,0)) -> 0
O143: =IF(G143="Reimbursement ","",I143+J143+K143+L143+M143) -> 0 | P143: =IF(G143="Reimbursement ","",H143-O143) -> 0 | S143: =IF(OR(R143="",Q143=""),0,IF(R143>Q143,R143-Q143,0)) -> 0
O144: =IF(G144="Reimbursement ","",I144+J144+K144+L144+M144) -> 0 | P144: =IF(G144="Reimbursement ","",H144-O144) -> 0 | S144: =IF(OR(R144="",Q144=""),0,IF(R144>Q144,R144-Q144,0)) -> 0
O145: =IF(G145="Reimbursement ","",I145+J145+K145+L145+M145) -> 0 | P145: =IF(G145="Reimbursement ","",H145-O145) -> 0 | S145: =IF(OR(R145="",Q145=""),0,IF(R145>Q145,R145-Q145,0)) -> 0
O146: =IF(G146="Reimbursement ","",I146+J146+K146+L146+M146) -> 0 | P146: =IF(G146="Reimbursement ","",H146-O146) -> 0 | S146: =IF(OR(R146="",Q146=""),0,IF(R146>Q146,R146-Q146,0)) -> 0
... O197: =IF(G197="Reimbursement ","",I197+J197+K197+L197+M197) -> 0 | P197: =IF(G197="Reimbursement ","",H197-O197) -> 0 | S197: =IF(OR(R197="",Q197=""),0,IF(R197>Q197,R197-Q197,0)) -> 0
O198: =#N/A -> #N/A | P198: =#N/A -> #N/A | S198: =IF(OR(R198="",Q198=""),0,IF(R198>Q198,R198-Q198,0)) -> 0
O199: =IF(G199="Reimbursement ","",I199+J199+K199+L199+M199) -> 0 | P199: =IF(G199="Reimbursement ","",H199-O199) -> 0 | S199: =IF(OR(R199="",Q199=""),0,IF(R199>Q199,R199-Q199,0)) -> 0
O200: =IF(G200="Reimbursement ","",I200+J200+K200+L200+M200) -> 0 | P200: =IF(G200="Reimbursement ","",H200-O200) -> 0 | S200: =IF(OR(R200="",Q200=""),0,IF(R200>Q200,R200-Q200,0)) -> 0
O201: =IF(G201="Reimbursement ","",I201+J201+K201+L201+M201) -> 0 | P201: =IF(G201="Reimbursement ","",H201-O201) -> 0 | S201: =IF(OR(R201="",Q201=""),0,IF(R201>Q201,R201-Q201,0)) -> 0
O202: =IF(G202="Reimbursement ","",I202+J202+K202+L202+M202) -> 0 | P202: =IF(G202="Reimbursement ","",H202-O202) -> 0 | S202: =IF(OR(R202="",Q202=""),0,IF(R202>Q202,R202-Q202,0)) -> 0
O203: =IF(G203="Reimbursement ","",I203+J203+K203+L203+M203) -> 0 | P203: =IF(G203="Reimbursement ","",H203-O203) -> 0 | S203: =IF(OR(R203="",Q203=""),0,IF(R203>Q203,R203-Q203,0)) -> 0
O204: =IF(G204="Reimbursement ","",I204+J204+K204+L204+M204) -> 0 | P204: =IF(G204="Reimbursement ","",H204-O204) -> 0 | S204: =IF(OR(R204="",Q204=""),0,IF(R204>Q204,R204-Q204,0)) -> 0
O205: =IF(G205="Reimbursement ","",I205+J205+K205+L205+M205) -> 0 | P205: =IF(G205="Reimbursement ","",H205-O205) -> 0 | S205: =IF(OR(R205="",Q205=""),0,IF(R205>Q205,R205-Q205,0)) -> 0
O206: =IF(G206="Reimbursement ","",I206+J206+K206+L206+M206) -> 0 | P206: =IF(G206="Reimbursement ","",H206-O206) -> 0 | S206: =IF(OR(R206="",Q206=""),0,IF(R206>Q206,R206-Q206,0)) -> 0
O207: =IF(G207="Reimbursement ","",I207+J207+K207+L207+M207) -> 0 | P207: =IF(G207="Reimbursement ","",H207-O207) -> 0 | S207: =IF(OR(R207="",Q207=""),0,IF(R207>Q207,R207-Q207,0)) -> 0
O208: =IF(G208="Reimbursement ","",I208+J208+K208+L208+M208) -> 0 | P208: =IF(G208="Reimbursement ","",H208-O208) -> 0 | S208: =IF(OR(R208="",Q208=""),0,IF(R208>Q208,R208-Q208,0)) -> 0
O209: =IF(G209="Reimbursement ","",I209+J209+K209+L209+M209) -> 0 | P209: =IF(G209="Reimbursement ","",H209-O209) -> 0 | S209: =IF(OR(R209="",Q209=""),0,IF(R209>Q209,R209-Q209,0)) -> 0
O210: =IF(G210="Reimbursement ","",I210+J210+K210+L210+M210) -> 0 | P210: =IF(G210="Reimbursement ","",H210-O210) -> 0 | S210: =IF(OR(R210="",Q210=""),0,IF(R210>Q210,R210-Q210,0)) -> 0
... O261: =IF(G261="Reimbursement ","",I261+J261+K261+L261+M261) -> 0 | P261: =IF(G261="Reimbursement ","",H261-O261) -> 0 | S261: =IF(OR(R261="",Q261=""),0,IF(R261>Q261,R261-Q261,0)) -> 0
O262: =#N/A -> #N/A | P262: =#N/A -> #N/A | S262: =IF(OR(R262="",Q262=""),0,IF(R262>Q262,R262-Q262,0)) -> 0
O263: =IF(G263="Reimbursement ","",I263+J263+K263+L263+M263) -> 0 | P263: =IF(G263="Reimbursement ","",H263-O263) -> 0 | S263: =IF(OR(R263="",Q263=""),0,IF(R263>Q263,R263-Q263,0)) -> 0
O264: =IF(G264="Reimbursement ","",I264+J264+K264+L264+M264) -> 0 | P264: =IF(G264="Reimbursement ","",H264-O264) -> 0 | S264: =IF(OR(R264="",Q264=""),0,IF(R264>Q264,R264-Q264,0)) -> 0
O265: =IF(G265="Reimbursement ","",I265+J265+K265+L265+M265) -> 0 | P265: =IF(G265="Reimbursement ","",H265-O265) -> 0 | S265: =IF(OR(R265="",Q265=""),0,IF(R265>Q265,R265-Q265,0)) -> 0
O266: =IF(G266="Reimbursement ","",I266+J266+K266+L266+M266) -> 0 | P266: =IF(G266="Reimbursement ","",H266-O266) -> 0 | S266: =IF(OR(R266="",Q266=""),0,IF(R266>Q266,R266-Q266,0)) -> 0
O267: =IF(G267="Reimbursement ","",I267+J267+K267+L267+M267) -> 0 | P267: =IF(G267="Reimbursement ","",H267-O267) -> 0 | S267: =IF(OR(R267="",Q267=""),0,IF(R267>Q267,R267-Q267,0)) -> 0
O268: =IF(G268="Reimbursement ","",I268+J268+K268+L268+M268) -> 0 | P268: =IF(G268="Reimbursement ","",H268-O268) -> 0 | S268: =IF(OR(R268="",Q268=""),0,IF(R268>Q268,R268-Q268,0)) -> 0
O269: =IF(G269="Reimbursement ","",I269+J269+K269+L269+M269) -> 0 | P269: =IF(G269="Reimbursement ","",H269-O269) -> 0 | S269: =IF(OR(R269="",Q269=""),0,IF(R269>Q269,R269-Q269,0)) -> 0
O270: =IF(G270="Reimbursement ","",I270+J270+K270+L270+M270) -> 0 | P270: =IF(G270="Reimbursement ","",H270-O270) -> 0 | S270: =IF(OR(R270="",Q270=""),0,IF(R270>Q270,R270-Q270,0)) -> 0
O271: =IF(G271="Reimbursement ","",I271+J271+K271+L271+M271) -> 0 | P271: =IF(G271="Reimbursement ","",H271-O271) -> 0 | S271: =IF(OR(R271="",Q271=""),0,IF(R271>Q271,R271-Q271,0)) -> 0
O272: =IF(G272="Reimbursement ","",I272+J272+K272+L272+M272) -> 0 | P272: =IF(G272="Reimbursement ","",H272-O272) -> 0 | S272: =IF(OR(R272="",Q272=""),0,IF(R272>Q272,R272-Q272,0)) -> 0
O273: =IF(G273="Reimbursement ","",I273+J273+K273+L273+M273) -> 0 | P273: =IF(G273="Reimbursement ","",H273-O273) -> 0 | S273: =IF(OR(R273="",Q273=""),0,IF(R273>Q273,R273-Q273,0)) -> 0
O274: =IF(G274="Reimbursement ","",I274+J274+K274+L274+M274) -> 0 | P274: =IF(G274="Reimbursement ","",H274-O274) -> 0 | S274: =IF(OR(R274="",Q274=""),0,IF(R274>Q274,R274-Q274,0)) -> 0
... O325: =IF(G325="Reimbursement ","",I325+J325+K325+L325+M325) -> 0 | P325: =IF(G325="Reimbursement ","",H325-O325) -> 0 | S325: =IF(OR(R325="",Q325=""),0,IF(R325>Q325,R325-Q325,0)) -> 0
O326: =#N/A -> #N/A | P326: =#N/A -> #N/A | S326: =IF(OR(R326="",Q326=""),0,IF(R326>Q326,R326-Q326,0)) -> 0
O327: =IF(G327="Reimbursement ","",I327+J327+K327+L327+M327) -> 0 | P327: =IF(G327="Reimbursement ","",H327-O327) -> 0 | S327: =IF(OR(R327="",Q327=""),0,IF(R327>Q327,R327-Q327,0)) -> 0
O328: =IF(G328="Reimbursement ","",I328+J328+K328+L328+M328) -> 0 | P328: =IF(G328="Reimbursement ","",H328-O328) -> 0 | S328: =IF(OR(R328="",Q328=""),0,IF(R328>Q328,R328-Q328,0)) -> 0
O329: =IF(G329="Reimbursement ","",I329+J329+K329+L329+M329) -> 0 | P329: =IF(G329="Reimbursement ","",H329-O329) -> 0 | S329: =IF(OR(R329="",Q329=""),0,IF(R329>Q329,R329-Q329,0)) -> 0
O330: =IF(G330="Reimbursement ","",I330+J330+K330+L330+M330) -> 0 | P330: =IF(G330="Reimbursement ","",H330-O330) -> 0 | S330: =IF(OR(R330="",Q330=""),0,IF(R330>Q330,R330-Q330,0)) -> 0
O331: =IF(G331="Reimbursement ","",I331+J331+K331+L331+M331) -> 0 | P331: =IF(G331="Reimbursement ","",H331-O331) -> 0 | S331: =IF(OR(R331="",Q331=""),0,IF(R331>Q331,R331-Q331,0)) -> 0
O332: =IF(G332="Reimbursement ","",I332+J332+K332+L332+M332) -> 0 | P332: =IF(G332="Reimbursement ","",H332-O332) -> 0 | S332: =IF(OR(R332="",Q332=""),0,IF(R332>Q332,R332-Q332,0)) -> 0
O333: =IF(G333="Reimbursement ","",I333+J333+K333+L333+M333) -> 0 | P333: =IF(G333="Reimbursement ","",H333-O333) -> 0 | S333: =IF(OR(R333="",Q333=""),0,IF(R333>Q333,R333-Q333,0)) -> 0
O334: =IF(G334="Reimbursement ","",I334+J334+K334+L334+M334) -> 0 | P334: =IF(G334="Reimbursement ","",H334-O334) -> 0 | S334: =IF(OR(R334="",Q334=""),0,IF(R334>Q334,R334-Q334,0)) -> 0
O335: =IF(G335="Reimbursement ","",I335+J335+K335+L335+M335) -> 0 | P335: =IF(G335="Reimbursement ","",H335-O335) -> 0 | S335: =IF(OR(R335="",Q335=""),0,IF(R335>Q335,R335-Q335,0)) -> 0
O336: =IF(G336="Reimbursement ","",I336+J336+K336+L336+M336) -> 0 | P336: =IF(G336="Reimbursement ","",H336-O336) -> 0 | S336: =IF(OR(R336="",Q336=""),0,IF(R336>Q336,R336-Q336,0)) -> 0
O337: =IF(G337="Reimbursement ","",I337+J337+K337+L337+M337) -> 0 | P337: =IF(G337="Reimbursement ","",H337-O337) -> 0 | S337: =IF(OR(R337="",Q337=""),0,IF(R337>Q337,R337-Q337,0)) -> 0
O338: =IF(G338="Reimbursement ","",I338+J338+K338+L338+M338) -> 0 | P338: =IF(G338="Reimbursement ","",H338-O338) -> 0 | S338: =IF(OR(R338="",Q338=""),0,IF(R338>Q338,R338-Q338,0)) -> 0
... O389: =IF(G389="Reimbursement ","",I389+J389+K389+L389+M389) -> 0 | P389: =IF(G389="Reimbursement ","",H389-O389) -> 0 | S389: =IF(OR(R389="",Q389=""),0,IF(R389>Q389,R389-Q389,0)) -> 0
...

Sheet Advances Summary
A1: OUTSTANDING ADVANCES — SITE SUMMARY
A2: Auto-updates from 'Transactions' sheet | D2: Month: | F2: Today's Date: | G2: =TODAY() -> 46156
A3: TOTAL ADVANCED (H) | C3: TOTAL ACCOUNTED | E3: REIMB PAID (R) | G3: NET OUTSTANDING
A4: =SUM(C16:C3015) -> 9187 | C4: =SUM(D16:D3015) -> 3900 | E4: =SUM(F16:F3015) -> 100 | G4: =SUM(G16:G3015) -> 1087
A5: STATUS: OUTSTANDING = X owes company | SETTLED = fully accounted, zero balance | OWES = company owes X (bills not fully paid) | OVERPAID = company already paid X more than owed
A6: ● OUTSTANDING | C6: ● SETTLED | E6: ● OWES | G6: ● OVERPAID
A8: HOW IT WORKS: Net = (Advanced + Reimb Paid) − (Cash Returned + Actual Expense + Bills Submitted) Example: Advance 500 → spend 200 → submit 500 bill → pay 200 (offset 300 debt) → Settled
A10: WORKER | C10: FINANCIAL BREAKDOWN | G10: NET RESULT
A11: # | B11: Worker / Payee | C11: Total Advanced | D11: Total Accounted | E11: Actual Expense | F11: Reimb Paid | G11: Net Outstanding | H11: Status
A13: TOTALS | C13: =SUM(C16:C3015) -> 9187 | D13: =SUM(D16:D3015) -> 3900 | E13: =SUM(E16:E3015) -> 700 | F13: =SUM(F16:F3015) -> 100 | G13: =SUM(G16:G3015) -> 1087 | H13: =SUM(H16:H3015) -> 0
A16: 1 | B16: {=IFERROR(IF(INDEX(Transactions!$F$8:$F$3006,MATCH(0,COUNTIF($B$11:B15,Transactions!$F$8:$F$3006),0))="","",INDEX(Transactions!$F$8:$F$3006,MATCH(0,COUNTIF($B$11:B15,Transactions!$F$8:$F$3006),0))),"")} -> Rey | C16: =IF(B16="","",SUMIF(Transactions!$F$8:$F$3006,B16,Transactions!$H$8:$H$3006)) -> 410 | D16: =IF(B16="","",SUMIF(Transactions!$F$8:$F$3006,B16,Transactions!$N$8:$N$3006)) -> 0 | E16: =IF(B16="","",SUMIF(Transactions!$F$8:$F$3006,B16,Transactions!$O$8:$O$3006)) -> 0 | F16: =IF(B16="","",SUMIF(Transactions!$F$8:$F$3006,B16,Transactions!$R$8:$R$3006)) -> 0 | G16: =IF(B16="","",(C16+F16)-(D16+E16+SUMIF(Transactions!$F$8:$F$3006,B16,Transactions!$Q$8:$Q$3006))) -> 410 | H16: =IF(B16="","",IF(G16>0,"OUTSTANDING",IF(G16=0,"SETTLED",IF(SUMIF(Transactions!$F$8:$F$3006,B16,Transactions!$Q$8:$Q$3006)>SUMIF(Transactions!$F$8:$F$3006,B16,Transactions!$R$8:$R$3006),"OWES","OVERPAID")))) -> OUTSTANDING
A17: 2 | B17: {=IFERROR(IF(INDEX(Transactions!$F$8:$F$3006,MATCH(0,COUNTIF($B$11:B16,Transactions!$F$8:$F$3006),0))="","",INDEX(Transactions!$F$8:$F$3006,MATCH(0,COUNTIF($B$11:B16,Transactions!$F$8:$F$3006),0))),"")} -> Ben | C17: =IF(B17="","",SUMIF(Transactions!$F$8:$F$3006,B17,Transactions!$H$8:$H$3006)) -> 18 | D17: =IF(B17="","",SUMIF(Transactions!$F$8:$F$3006,B17,Transactions!$N$8:$N$3006)) -> 0 | E17: =IF(B17="","",SUMIF(Transactions!$F$8:$F$3006,B17,Transactions!$O$8:$O$3006)) -> 0 | F17: =IF(B17="","",SUMIF(Transactions!$F$8:$F$3006,B17,Transactions!$R$8:$R$3006)) -> 0 | G17: =IF(B17="","",(C17+F17)-(D17+E17+SUMIF(Transactions!$F$8:$F$3006,B17,Transactions!$Q$8:$Q$3006))) -> 18 | H17: =IF(B17="","",IF(G17>0,"OUTSTANDING",IF(G17=0,"SETTLED",IF(SUMIF(Transactions!$F$8:$F$3006,B17,Transactions!$Q$8:$Q$3006)>SUMIF(Transactions!$F$8:$F$3006,B17,Transactions!$R$8:$R$3006),"OWES","OVERPAID")))) -> OUTSTANDING
A18: 3 | B18: {=IFERROR(IF(INDEX(Transactions!$F$8:$F$3006,MATCH(0,COUNTIF($B$11:B17,Transactions!$F$8:$F$3006),0))="","",INDEX(Transactions!$F$8:$F$3006,MATCH(0,COUNTIF($B$11:B17,Transactions!$F$8:$F$3006),0))),"")} -> Cal | C18: =IF(B18="","",SUMIF(Transactions!$F$8:$F$3006,B18,Transactions!$H$8:$H$3006)) -> 2 | D18: =IF(B18="","",SUMIF(Transactions!$F$8:$F$3006,B18,Transactions!$N$8:$N$3006)) -> 0 | E18: =IF(B18="","",SUMIF(Transactions!$F$8:$F$3006,B18,Transactions!$O$8:$O$3006)) -> 0 | F18: =IF(B18="","",SUMIF(Transactions!$F$8:$F$3006,B18,Transactions!$R$8:$R$3006)) -> 0 | G18: =IF(B18="","",(C18+F18)-(D18+E18+SUMIF(Transactions!$F$8:$F$3006,B18,Transactions!$Q$8:$Q$3006))) -> 2 | H18: =IF(B18="","",IF(G18>0,"OUTSTANDING",IF(G18=0,"SETTLED",IF(SUMIF(Transactions!$F$8:$F$3006,B18,Transactions!$Q$8:$Q$3006)>SUMIF(Transactions!$F$8:$F$3006,B18,Transactions!$R$8:$R$3006),"OWES","OVERPAID")))) -> OUTSTANDING
A19: 4 | B19: {=IFERROR(IF(INDEX(Transactions!$F$8:$F$3006,MATCH(0,COUNTIF($B$11:B18,Transactions!$F$8:$F$3006),0))="","",INDEX(Transactions!$F$8:$F$3006,MATCH(0,COUNTIF($B$11:B18,Transactions!$F$8:$F$3006),0))),"")} -> Dan | C19: =IF(B19="","",SUMIF(Transactions!$F$8:$F$3006,B19,Transactions!$H$8:$H$3006)) -> 10 | D19: =IF(B19="","",SUMIF(Transactions!$F$8:$F$3006,B19,Transactions!$N$8:$N$3006)) -> 0 | E19: =IF(B19="","",SUMIF(Transactions!$F$8:$F$3006,B19,Transactions!$O$8:$O$3006)) -> 0 | F19: =IF(B19="","",SUMIF(Transactions!$F$8:$F$3006,B19,Transactions!$R$8:$R$3006)) -> 0 | G19: =IF(B19="","",(C19+F19)-(D19+E19+SUMIF(Transactions!$F$8:$F$3006,B19,Transactions!$Q$8:$Q$3006))) -> 10 | H19: =IF(B19="","",IF(G19>0,"OUTSTANDING",IF(G19=0,"SETTLED",IF(SUMIF(Transactions!$F$8:$F$3006,B19,Transactions!$Q$8:$Q$3006)>SUMIF(Transactions!$F$8:$F$3006,B19,Transactions!$R$8:$R$3006),"OWES","OVERPAID")))) -> OUTSTANDING
A20: 5 | B20: {=IFERROR(IF(INDEX(Transactions!$F$8:$F$3006,MATCH(0,COUNTIF($B$11:B19,Transactions!$F$8:$F$3006),0))="","",INDEX(Transactions!$F$8:$F$3006,MATCH(0,COUNTIF($B$11:B19,Transactions!$F$8:$F$3006),0))),"")} -> Eli | C20: =IF(B20="","",SUMIF(Transactions!$F$8:$F$3006,B20,Transactions!$H$8:$H$3006)) -> 500 | D20: =IF(B20="","",SUMIF(Transactions!$F$8:$F$3006,B20,Transactions!$N$8:$N$3006)) -> 0 | E20: =IF(B20="","",SUMIF(Transactions!$F$8:$F$3006,B20,Transactions!$O$8:$O$3006)) -> 0 | F20: =IF(B20="","",SUMIF(Transactions!$F$8:$F$3006,B20,Transactions!$R$8:$R$3006)) -> 0 | G20: =IF(B20="","",(C20+F20)-(D20+E20+SUMIF(Transactions!$F$8:$F$3006,B20,Transactions!$Q$8:$Q$3006))) -> 500 | H20: =IF(B20="","",IF(G20>0,"OUTSTANDING",IF(G20=0,"SETTLED",IF(SUMIF(Transactions!$F$8:$F$3006,B20,Transactions!$Q$8:$Q$3006)>SUMIF(Transactions!$F$8:$F$3006,B20,Transactions!$R$8:$R$3006),"OWES","OVERPAID")))) -> OUTSTANDING
A21: 6 | B21: {=IFERROR(IF(INDEX(Transactions!$F$8:$F$3006,MATCH(0,COUNTIF($B$11:B20,Transactions!$F$8:$F$3006),0))="","",INDEX(Transactions!$F$8:$F$3006,MATCH(0,COUNTIF($B$11:B20,Transactions!$F$8:$F$3006),0))),"")} -> Ian | C21: =IF(B21="","",SUMIF(Transactions!$F$8:$F$3006,B21,Transactions!$H$8:$H$3006)) -> 500 | D21: =IF(B21="","",SUMIF(Transactions!$F$8:$F$3006,B21,Transactions!$N$8:$N$3006)) -> 0 | E21: =IF(B21="","",SUMIF(Transactions!$F$8:$F$3006,B21,Transactions!$O$8:$O$3006)) -> 0 | F21: =IF(B21="","",SUMIF(Transactions!$F$8:$F$3006,B21,Transactions!$R$8:$R$3006)) -> 0 | G21: =IF(B21="","",(C21+F21)-(D21+E21+SUMIF(Transactions!$F$8:$F$3006,B21,Transactions!$Q$8:$Q$3006))) -> 500 | H21: =IF(B21="","",IF(G21>0,"OUTSTANDING",IF(G21=0,"SETTLED",IF(SUMIF(Transactions!$F$8:$F$3006,B21,Transactions!$Q$8:$Q$3006)>SUMIF(Transactions!$F$8:$F$3006,B21,Transactions!$R$8:$R$3006),"OWES","OVERPAID")))) -> OUTSTANDING
A22: 7 | B22: {=IFERROR(IF(INDEX(Transactions!$F$8:$F$3006,MATCH(0,COUNTIF($B$11:B21,Transactions!$F$8:$F$3006),0))="","",INDEX(Transactions!$F$8:$F$3006,MATCH(0,COUNTIF($B$11:B21,Transactions!$F$8:$F$3006),0))),"")} -> Jay | C22: =IF(B22="","",SUMIF(Transactions!$F$8:$F$3006,B22,Transactions!$H$8:$H$3006)) -> 1000 | D22: =IF(B22="","",SUMIF(Transactions!$F$8:$F$3006,B22,Transactions!$N$8:$N$3006)) -> 0 | E22: =IF(B22="","",SUMIF(Transactions!$F$8:$F$3006,B22,Transactions!$O$8:$O$3006)) -> 0 | F22: =IF(B22="","",SUMIF(Transactions!$F$8:$F$3006,B22,Transactions!$R$8:$R$3006)) -> 0 | G22: =IF(B22="","",(C22+F22)-(D22+E22+SUMIF(Transactions!$F$8:$F$3006,B22,Transactions!$Q$8:$Q$3006))) -> 1000 | H22: =IF(B22="","",IF(G22>0,"OUTSTANDING",IF(G22=0,"SETTLED",IF(SUMIF(Transactions!$F$8:$F$3006,B22,Transactions!$Q$8:$Q$3006)>SUMIF(Transactions!$F$8:$F$3006,B22,Transactions!$R$8:$R$3006),"OWES","OVERPAID")))) -> OUTSTANDING
A23: 8 | B23: {=IFERROR(IF(INDEX(Transactions!$F$8:$F$3006,MATCH(0,COUNTIF($B$11:B22,Transactions!$F$8:$F$3006),0))="","",INDEX(Transactions!$F$8:$F$3006,MATCH(0,COUNTIF($B$11:B22,Transactions!$F$8:$F$3006),0))),"")} -> Kai | C23: =IF(B23="","",SUMIF(Transactions!$F$8:$F$3006,B23,Transactions!$H$8:$H$3006)) -> 0 | D23: =IF(B23="","",SUMIF(Transactions!$F$8:$F$3006,B23,Transactions!$N$8:$N$3006)) -> 200 | E23: =IF(B23="","",SUMIF(Transactions!$F$8:$F$3006,B23,Transactions!$O$8:$O$3006)) -> 0 | F23: =IF(B23="","",SUMIF(Transactions!$F$8:$F$3006,B23,Transactions!$R$8:$R$3006)) -> 0 | G23: =IF(B23="","",(C23+F23)-(D23+E23+SUMIF(Transactions!$F$8:$F$3006,B23,Transactions!$Q$8:$Q$3006))) -> -200 | H23: =IF(B23="","",IF(G23>0,"OUTSTANDING",IF(G23=0,"SETTLED",IF(SUMIF(Transactions!$F$8:$F$3006,B23,Transactions!$Q$8:$Q$3006)>SUMIF(Transactions!$F$8:$F$3006,B23,Transactions!$R$8:$R$3006),"OWES","OVERPAID")))) -> OVERPAID
A24: 9 | B24: {=IFERROR(IF(INDEX(Transactions!$F$8:$F$3006,MATCH(0,COUNTIF($B$11:B23,Transactions!$F$8:$F$3006),0))="","",INDEX(Transactions!$F$8:$F$3006,MATCH(0,COUNTIF($B$11:B23,Transactions!$F$8:$F$3006),0))),"")} -> Leo | C24: =IF(B24="","",SUMIF(Transactions!$F$8:$F$3006,B24,Transactions!$H$8:$H$3006)) -> 1000 | D24: =IF(B24="","",SUMIF(Transactions!$F$8:$F$3006,B24,Transactions!$N$8:$N$3006)) -> 500 | E24: =IF(B24="","",SUMIF(Transactions!$F$8:$F$3006,B24,Transactions!$O$8:$O$3006)) -> 0 | F24: =IF(B24="","",SUMIF(Transactions!$F$8:$F$3006,B24,Transactions!$R$8:$R$3006)) -> 0 | G24: =IF(B24="","",(C24+F24)-(D24+E24+SUMIF(Transactions!$F$8:$F$3006,B24,Transactions!$Q$8:$Q$3006))) -> 500 | H24: =IF(B24="","",IF(G24>0,"OUTSTANDING",IF(G24=0,"SETTLED",IF(SUMIF(Transactions!$F$8:$F$3006,B24,Transactions!$Q$8:$Q$3006)>SUMIF(Transactions!$F$8:$F$3006,B24,Transactions!$R$8:$R$3006),"OWES","OVERPAID")))) -> OUTSTANDING
A25: 10 | B25: {=IFERROR(IF(INDEX(Transactions!$F$8:$F$3006,MATCH(0,COUNTIF($B$11:B24,Transactions!$F$8:$F$3006),0))="","",INDEX(Transactions!$F$8:$F$3006,MATCH(0,COUNTIF($B$11:B24,Transactions!$F$8:$F$3006),0))),"")} -> Max | C25: =IF(B25="","",SUMIF(Transactions!$F$8:$F$3006,B25,Transactions!$H$8:$H$3006)) -> 0 | D25: =IF(B25="","",SUMIF(Transactions!$F$8:$F$3006,B25,Transactions!$N$8:$N$3006)) -> 300 | E25: =IF(B25="","",SUMIF(Transactions!$F$8:$F$3006,B25,Transactions!$O$8:$O$3006)) -> 0 | F25: =IF(B25="","",SUMIF(Transactions!$F$8:$F$3006,B25,Transactions!$R$8:$R$3006)) -> 0 | G25: =IF(B25="","",(C25+F25)-(D25+E25+SUMIF(Transactions!$F$8:$F$3006,B25,Transactions!$Q$8:$Q$3006))) -> -300 | H25: =IF(B25="","",IF(G25>0,"OUTSTANDING",IF(G25=0,"SETTLED",IF(SUMIF(Transactions!$F$8:$F$3006,B25,Transactions!$Q$8:$Q$3006)>SUMIF(Transactions!$F$8:$F$3006,B25,Transactions!$R$8:$R$3006),"OWES","OVERPAID")))) -> OVERPAID
A26: 11 | B26: {=IFERROR(IF(INDEX(Transactions!$F$8:$F$3006,MATCH(0,COUNTIF($B$11:B25,Transactions!$F$8:$F$3006),0))="","",INDEX(Transactions!$F$8:$F$3006,MATCH(0,COUNTIF($B$11:B25,Transactions!$F$8:$F$3006),0))),"")} -> Neo | C26: =IF(B26="","",SUMIF(Transactions!$F$8:$F$3006,B26,Transactions!$H$8:$H$3006)) -> 0 | D26: =IF(B26="","",SUMIF(Transactions!$F$8:$F$3006,B26,Transactions!$N$8:$N$3006)) -> 0 | E26: =IF(B26="","",SUMIF(Transactions!$F$8:$F$3006,B26,Transactions!$O$8:$O$3006)) -> 0 | F26: =IF(B26="","",SUMIF(Transactions!$F$8:$F$3006,B26,Transactions!$R$8:$R$3006)) -> 0 | G26: =IF(B26="","",(C26+F26)-(D26+E26+SUMIF(Transactions!$F$8:$F$3006,B26,Transactions!$Q$8:$Q$3006))) -> -600 | H26: =IF(B26="","",IF(G26>0,"OUTSTANDING",IF(G26=0,"SETTLED",IF(SUMIF(Transactions!$F$8:$F$3006,B26,Transactions!$Q$8:$Q$3006)>SUMIF(Transactions!$F$8:$F$3006,B26,Transactions!$R$8:$R$3006),"OWES","OVERPAID")))) -> OWES
A27: 12 | B27: {=IFERROR(IF(INDEX(Transactions!$F$8:$F$3006,MATCH(0,COUNTIF($B$11:B26,Transactions!$F$8:$F$3006),0))="","",INDEX(Transactions!$F$8:$F$3006,MATCH(0,COUNTIF($B$11:B26,Transactions!$F$8:$F$3006),0))),"")} -> Oli | C27: =IF(B27="","",SUMIF(Transactions!$F$8:$F$3006,B27,Transactions!$H$8:$H$3006)) -> 1000 | D27: =IF(B27="","",SUMIF(Transactions!$F$8:$F$3006,B27,Transactions!$N$8:$N$3006)) -> 0 | E27: =IF(B27="","",SUMIF(Transactions!$F$8:$F$3006,B27,Transactions!$O$8:$O$3006)) -> 0 | F27: =IF(B27="","",SUMIF(Transactions!$F$8:$F$3006,B27,Transactions!$R$8:$R$3006)) -> 0 | G27: =IF(B27="","",(C27+F27)-(D27+E27+SUMIF(Transactions!$F$8:$F$3006,B27,Transactions!$Q$8:$Q$3006))) -> 1000 | H27: =IF(B27="","",IF(G27>0,"OUTSTANDING",IF(G27=0,"SETTLED",IF(SUMIF(Transactions!$F$8:$F$3006,B27,Transactions!$Q$8:$Q$3006)>SUMIF(Transactions!$F$8:$F$3006,B27,Transactions!$R$8:$R$3006),"OWES","OVERPAID")))) -> OUTSTANDING
... A3015: 3000 | B3015: {=IFERROR(IF(INDEX(Transactions!$F$8:$F$3006,MATCH(0,COUNTIF($B$11:B3014,Transactions!$F$8:$F$3006),0))="","",INDEX(Transactions!$F$8:$F$3006,MATCH(0,COUNTIF($B$11:B3014,Transactions!$F$8:$F$3006),0))),"")} | C3015: =IF(B3015="","",SUMIF(Transactions!$F$8:$F$3006,B3015,Transactions!$H$8:$H$3006)) | D3015: =IF(B3015="","",SUMIF(Transactions!$F$8:$F$3006,B3015,Transactions!$N$8:$N$3006)) | E3015: =IF(B3015="","",SUMIF(Transactions!$F$8:$F$3006,B3015,Transactions!$O$8:$O$3006)) | F3015: =IF(B3015="","",SUMIF(Transactions!$F$8:$F$3006,B3015,Transactions!$R$8:$R$3006)) | G3015: =IF(B3015="","",(C3015+F3015)-(D3015+E3015+SUMIF(Transactions!$F$8:$F$3006,B3015,Transactions!$Q$8:$Q$3006))) | H3015: =IF(B3015="","",IF(G3015>0,"OUTSTANDING",IF(G3015=0,"SETTLED",IF(SUMIF(Transactions!$F$8:$F$3006,B3015,Transactions!$Q$8:$Q$3006)>SUMIF(Transactions!$F$8:$F$3006,B3015,Transactions!$R$8:$R$3006),"OWES","OVERPAID"))))

Sheet Guide
A1: PETTY CASH BOOK — REFERENCE GUIDE
A2: Discovery Dunes Site | Complete guide to using this workbook correctly
B4: 1. WHAT IS PETTY CASH?
B5: Purpose | C5: Petty cash is a small reserve of money kept on-site to cover minor day-to-day expenses (fuel, food, materials, small services) without going through the main accounts process. This workbook tracks every dirham in and out.
B6: How it flows | C6: Company sends cash to site (replenishment) → Site manager advances money to site team members → Site Team Members spend and return receipts or leftover cash → Manager records everything → Outstanding Advances sheet shows who owes what at all times.
B7: Two sheets | C7: PETTY CASH BOOK = every individual transaction. OUTSTANDING ADVANCES = one summarised line per site team member showing their running balance. The Outstanding sheet updates automatically — do not edit it directly.
B9: 2. PETTY CASH BOOK — COLUMN GUIDE
B10: CASH-IN (Replenishments) — Columns A, B, C
B11: A — Date | C11: Date the replenishment cash was received from Head Office or management.
B12: B — Description | C12: Brief note on the source of funds. e.g. 'Received from HO', 'Balance c/d from previous month'.
B13: C — Amount Received | C13: The actual cash amount received. This adds to the total cash-in and feeds the Closing Balance KPI.
B15: VOUCHER / ADVANCE DETAILS — Columns D, E, F, G, H
B16: D — Ref. No. | C16: Voucher reference number. Use a consistent format e.g. V-001, V-002. Each advance or transaction should have a unique reference for traceability.
B17: E — Voucher Date | C17: The date the advance was given or the transaction occurred. May differ from the Cash-In date in column A.
B18: F — Payee / Site Team Member | C18: Name of the person who received the advance or submitted the bill. This name is used by the Outstanding Advances sheet to group all transactions for that person. Spelling must be consistent — 'Ahmed' and 'AHMED' are treated as two different people.
B19: G — Purpose | C19: Nature of the transaction. Use: Advance / Returned / Reimbursement / Balance.
B20: H — Amount Advanced | C20: Cash given to the site team member as an advance. This increases what the site team member owes the company.
B22: EXPENSE BREAKDOWN — Columns I, J, K, L, M
B23: I — Fuel | C23: Amount spent on fuel, verified by receipt or bill.
B24: J — Service / Labour | C24: Amount spent on labour or services, verified by receipt.
B25: K — Materials | C25: Amount spent on materials or supplies, verified by receipt.
B26: L — Food Allowance | C26: Amount spent on food or meal allowances, verified by receipt.
B27: M — Others | C27: Any other miscellaneous expense not covered by the above categories.
B28: O — Actual Expense (auto) | C28: Auto-calculated: sum of columns I+J+K+L+M. Do not edit. Represents total proven spending by the site team member — reduces their outstanding balance.
B30: SETTLEMENT — Columns N, P, Q, R, S
B31: N — Balance Returned | C31: Cash physically handed back by the site team member. If X received 500 and spent 200, they return 300 in cash → enter 300 here.
B32: P — Variance (auto) | C32: Auto-calculated: Amount Advanced (H) minus Actual Expense (O). Shows the unaccounted gap. Should be zero when a transaction is fully settled.
B33: Q — Reimb. Amount | C33: The bill amount the site team member is submitting for reimbursement. e.g. Site Team Member paid 500 from their own pocket for materials → enter 500.
B34: R — Reimb. Paid | C34: The actual cash YOU paid out to the site team member for the reimbursement. This may be less than Q if you deduct an outstanding advance. e.g. Site Team Member submits 500 bill but owes 300 advance → you pay 200, enter 200 here.
B35: S — Change Due Back (auto) | C35: Auto-calculated: if Reimb. Paid (R) is more than the bill (Q), the excess is change the site team member must return. e.g. No change available, you pay 1000 for a 500 bill → 500 change is automatically tracked as outstanding on that site team member.
B37: 3. OUTSTANDING ADVANCES — COLUMN GUIDE
B38: B — Site Team Member / Payee | C38: Auto-populated from the Petty Cash Book. Every unique name in column F of PCB automatically gets a row here. Do not type names manually in this column.
B39: C — Total Advanced | C39: Sum of all advances (column H) given to this site team member across all entries.
B40: D — Total Returned | C40: Sum of all cash returned (column N) by this site team member.
B41: E — Actual Expense | C41: Sum of all proven expenses (column O) by this site team member, supported by receipts.
B42: F — Reimb. Paid | C42: Sum of all reimbursement payments (column R) made to this site team member.
B43: G — Net Outstanding | C43: The single most important number. Formula: (Advanced + Reimb Paid) − (Returned + Actual Expense + Bills Submitted). Positive = site team member owes company. Negative = company owes site team member.
B44: H — Status | C44: Auto-assigned based on Net Outstanding. See Section 5 for full status definitions.
B46: 4. HOW THE BALANCE IS CALCULATED
B47: The formula | C47: Net Outstanding = (Amount Advanced + Reimb. Paid) − (Cash Returned + Actual Expense + Bills Submitted)
B48: In plain English | C48: Everything the company paid out to the site team member (cash advances + reimbursements), minus everything accounted for (cash returned + receipts proven + bills submitted). The difference is what remains unresolved.
B49: WORKED EXAMPLES
B50: Example 1 — Simple advance | C50: X receives AED 500 advance. Spends 100 fuel + 100 materials = 200. Returns 200 cash. Net = (500 + 0) − (200 + 200 + 0) = 100 OUTSTANDING (X still owes 100)
B51: Example 2 — Bill offsetting advance | C51: X receives AED 500 advance. Spends 200 (expense). Submits AED 500 bill. You pay 200 (deducting 300 old debt). Net = (500 + 200) − (0 + 200 + 500) = 0 SETTLED
B52: Example 3 — Reimbursement with no change | C52: X submits AED 500 bill. You only have 1000, so you pay 1000. Change due back = 500. Net = (0 + 1000) − (0 + 0 + 500) = 500 OUTSTANDING (X must return 500 change)
B53: Example 4 — Company owes site team member | C53: X has no advance. Submits AED 500 bill. You have only paid 200 so far. Net = (0 + 200) − (0 + 0 + 500) = −300 OWES (company still owes X 300)
B54: Example 5 — Advance + large bill | C54: X receives AED 1000 advance. Later submits AED 2000 bill. You pay 2000. Net = (1000 + 2000) − (0 + 0 + 2000) = 1000 OUTSTANDING (original advance still owed)
B56: 5. STATUS DEFINITIONS
B57: ● OUTSTANDING | C57: Site Team Member owes money to the company. Net Outstanding > 0. Action: Follow up with the site team member to recover cash or obtain supporting receipts.
B58: ● SETTLED | C58: All advances and reimbursements are fully accounted for. Net = 0. No further action required for this site team member.
B59: ● OWES | C59: Company owes money to the site team member. Bills have been submitted but not fully paid yet. Net < 0 and unpaid bills exist. Action: Process the outstanding reimbursement payment.
B60: ● OVERPAID | C60: Company has already paid the site team member more than what was owed. Net < 0 and all bills are settled. This may indicate a data entry error or an unrecorded transaction. Action: Investigate and recover excess.
B62: 6. IMPORTANT RULES & THINGS TO OBSERVE
B63: ⚠ Name consistency | C63: The Outstanding Advances sheet groups transactions by the exact name in column F. 'Ahmed', 'AHMED', and 'ahmed' are treated as THREE different people. Always use the same spelling and capitalisation for each site team member.
B65: ⚠ Never edit the Outstanding sheet directly | C65: The Outstanding Advances sheet is fully automatic. All data flows from the Petty Cash Book. If you manually type into the Outstanding sheet, it will break the auto-update formulas.
B67: ⚠ Always enter Reimb. Paid (col R) | C67: When you pay a site team member for a bill (reimbursement), you MUST enter the actual amount you paid in column R (Reimb. Paid), not just the bill amount in Q. If R is left blank, the Net Outstanding will be incorrect.
B69: ⚠ Update Opening Balance when starting a new month | C69: Cell E5 in the Petty Cash Book holds the opening balance. When starting a new month, update this to the closing balance from the previous month. This ensures the Total Cash-In and Closing Balance KPIs are accurate.
B71: ⚠ Record change due back immediately | C71: If you pay more than a bill because you have no change, enter the full amount in R. The system auto-calculates the change in column S. Make sure to recover the change from the site team member and record it when received (via column N).
B73: ⚠ Variance column (P) should ideally be zero | C73: Column P shows Advanced minus Actual Expense. If a site team member spent all their advance on proven expenses and returned the rest, the variance should be 0 when fully settled. A non-zero variance means cash is still unaccounted.
B75: ⚠ Do not skip Ref. No. (column D) | C75: Every voucher must have a unique reference number for audit purposes. Maintain a running sequence (V-001, V-002...) so any transaction can be traced back to a physical voucher or receipt.
B77: ⚠ Reimbursement vs Advance — key difference | C77: An ADVANCE is money given to a site team member before they spend it (they owe it back). A REIMBURSEMENT is money paid back to a site team member after they have already spent their own money. Record these correctly in column G (Purpose) to keep the Outstanding list accurate.
B80: 7. PURPOSE CODES — COLUMN G
B81: Advance | C81: Cash given to a site team member before they spend it. Creates an outstanding balance on the site team member.
B82: Returned | C82: Site Team Member has returned leftover cash from a previous advance. Reduces their outstanding balance.
B83: Reimbursement | C83: Site Team Member paid expenses from their own pocket and is submitting a bill for repayment. Enter the bill amount in Q and the actual amount you paid in R.
B84: Balance | C84: Used to bring forward an outstanding balance from a previous period or entry. e.g. recording an old advance that wasn't in the previous book.
B86: 8. KPI DASHBOARD (TOP OF EACH SHEET)
B87: Total Cash-In | C87: Opening Balance + all replenishments received (column C). This is the total funds available to the site petty cash.
B88: Total Advanced | C88: Sum of all advances issued (column H). Money currently out with site team members.
B89: Total Returned | C89: Sum of all cash returned (column N). Money physically back in the box.
B90: Closing Balance | C90: Total Cash-In − Total Advanced + Total Returned − Total Reimb Paid. This is the expected cash remaining in the petty cash box. Physically count the box and compare — any difference is a discrepancy to investigate.
B91: Net Outstanding (OA sheet) | C91: Total net balance across all site team members. Positive = site team members collectively owe the company. Negative = company collectively owes site team members. Target: as close to zero as possible.
A93: This document is auto-maintained. Do not edit formulas. For issues, contact the Finance team.
